benchmarkst/__init__.py
benchmarkst/benchmark_scgen.py
benchmarkst/benchmark_scvi.py
benchmarkst/benchmark_stvae.py
benchmarkst/benchmark_trvae.py
stvae/__init__.py
stvae/benchmark.py
stvae/config.py
stvae/experiment.py
stvae/preprocessing.py
stvae/stvae.py
stvae/test_script.py
stvae/train_script.py
stvae/update.py
stvae/utils.py
stvae/data/__init__.py
stvae/data/anndata.py
stvae/data/utils.py
stvae/datasets/__init__.py
stvae/datasets/mouse_dataset.py
stvae/model/__init__.py
stvae/model/autoencoders.py
stvae/model/classifier.py
stvae/model/dcgan.py
stvae/model/losses.py
stvae/model/ml.py
stvae/model/mmd.py
stvae/model/modules.py
stVAE-0.2.10.dist-info/METADATA
stVAE-0.2.10.dist-info/WHEEL
stVAE-0.2.10.dist-info/top_level.txt
stVAE-0.2.10.dist-info/RECORD
