Metadata-Version: 2.1
Name: stVAE
Version: 0.2.10
Summary: Style transfer variational autoencoder
Home-page: https://github.com/NRshka/stvae/source
Author: ['N. Russkikh', 'A. Makarov', 'D. Antonets', 'D. Shtokalo', 'Y. Vyatkin']
Author-email: makarov.alxr@yandex.ru
License: MIT license
Platform: UNKNOWN
Classifier: Development Status :: 4 - Beta
Classifier: Intended Audience :: Science/Research
Classifier: License :: OSI Approved :: MIT License
Classifier: Natural Language :: English
Classifier: Natural Language :: Russian
Classifier: Programming Language :: Python :: 3.7
Classifier: Operating System :: Microsoft :: Windows
Classifier: Operating System :: POSIX :: Linux
Classifier: Topic :: Scientific/Engineering :: Bio-Informatics
Requires-Python: >=3.6
Requires-Dist: dataclasses (==0.7)
Requires-Dist: torch
Requires-Dist: pytorch-ignite (==0.3.0)
Requires-Dist: numpy
Requires-Dist: pandas (==1.1.1)
Requires-Dist: typing
Requires-Dist: tensorboardX (==2.0)
Requires-Dist: scikit-learn (==0.23.2)
Requires-Dist: scipy (==1.4.1)
Requires-Dist: scvi
Requires-Dist: scanpy
Requires-Dist: torch-optimizer (==0.0.1a11)
Requires-Dist: scgen
Requires-Dist: requests
